fs_watcher/__init__.py
fs_watcher/__main__.py
fs_watcher/cli.py
fs_watcher/daemonrunner.py
fs_watcher/eventhandler.py
fs_watcher/watcher.py
fs_watcher-1.0.11.data/data/share/fs-watcher/etc/watcher.ini
fs_watcher-1.0.11.data/data/share/fs-watcher/init/fs-watcher.openrc
fs_watcher-1.0.11.data/data/share/fs-watcher/init/fs-watcher.service
fs_watcher-1.0.11.data/data/share/fs-watcher/init/fs-watcher.sysvinit
fs_watcher-1.0.11.dist-info/LICENSE
fs_watcher-1.0.11.dist-info/METADATA
fs_watcher-1.0.11.dist-info/WHEEL
fs_watcher-1.0.11.dist-info/entry_points.txt
fs_watcher-1.0.11.dist-info/top_level.txt
fs_watcher-1.0.11.dist-info/RECORD
