Metadata-Version: 2.1
Name: fs-watcher
Version: 1.0.11
Summary: Daemon that watches specified files/folders for changes and fires commands in response to those changes
Home-page: https://github.com/paleg/Watcher
Maintainer: Oleh Palii
Maintainer-email: o.palij@gmail.com
License: MIT
Download-URL: https://github.com/paleg/Watcher/releases
Keywords: inotify,filesystem,python,watcher
Platform: Linux
Classifier: Operating System :: POSIX :: Linux
Classifier: Programming Language :: Python
Classifier: Programming Language :: Python :: 3
Classifier: Programming Language :: Python :: 3.7
Classifier: Programming Language :: Python :: 3.9
Classifier: Development Status :: 5 - Production/Stable
Classifier: Environment :: Console
Classifier: License :: OSI Approved :: MIT License
Requires-Dist: future
Requires-Dist: pyinotify
Requires-Dist: python-daemon
Requires-Dist: lockfile
Requires-Dist: chardet
